pyawslog/__init__.py
pyawslog/pyawslog.py
pyawslog-0.1.5.dist-info/LICENSE
pyawslog-0.1.5.dist-info/METADATA
pyawslog-0.1.5.dist-info/WHEEL
pyawslog-0.1.5.dist-info/top_level.txt
pyawslog-0.1.5.dist-info/RECORD
