Metadata-Version: 2.1
Name: pyawslog
Version: 0.1.5
Summary: Python AWS Custom Log
Home-page: https://github.com/catchmaurya/pyawslog
Author: Maurya Allimuthu
Author-email: catchmaurya@gmail.com
License: UNKNOWN
Platform: UNKNOWN
Classifier: Programming Language :: Python :: 3
Classifier: License :: OSI Approved :: MIT License
Classifier: Operating System :: OS Independent
Requires-Dist: boto3 (>=1.9)
